sort_requirements_file/__init__.py
sort_requirements_file/__main__.py
sort_requirements_file-0.0.1.dist-info/LICENSE
sort_requirements_file-0.0.1.dist-info/METADATA
sort_requirements_file-0.0.1.dist-info/WHEEL
sort_requirements_file-0.0.1.dist-info/top_level.txt
sort_requirements_file-0.0.1.dist-info/RECORD
